plymouth_commons/__init__.py
plymouth_commons/auth.py
plymouth_commons/config.py
plymouth_commons/postgres.py
plymouth_commons-0.0.3.dist-info/METADATA
plymouth_commons-0.0.3.dist-info/WHEEL
plymouth_commons-0.0.3.dist-info/RECORD
