Metadata-Version: 2.1
Name: plymouth-commons
Version: 0.0.3
Summary: Common utilities for internal use at Plymouth Street
License: Proprietary
Author: Roshan Pawar
Author-email: steradian614@gmail.com
Requires-Python: >=3.11,<4.0
Classifier: License :: Other/Proprietary License
Classifier: Programming Language :: Python :: 3
Classifier: Programming Language :: Python :: 3.11
Classifier: Programming Language :: Python :: 3.12
Requires-Dist: asyncpg (>=0.29.0,<0.30.0)
Requires-Dist: cryptography (>=42.0.2,<43.0.0)
Requires-Dist: fastapi (>=0.109.2,<0.110.0)
Requires-Dist: pyjwt (>=2.8.0,<3.0.0)
